[
    {
        "name": "dashboard.view",
        "description": "Ver Dashboard",
        "guard": "web",
        "categoria": "Dashboard"
    },
    {
        "name": "roles.list",
        "description": "Listar Roles",
        "guard": "web",
        "categoria": "Seguridad"
    },
    {
        "name": "roles.view",
        "description": "Ver Rol",
        "guard": "web",
        "categoria": "Seguridad"
    },
    {
        "name": "roles.create",
        "description": "Crear Rol",
        "guard": "web",
        "categoria": "Seguridad"
    },
    {
        "name": "roles.edit",
        "description": "Editar Rol",
        "guard": "web",
        "categoria": "Seguridad"
    },
    {
        "name": "roles.delete",
        "description": "Eliminar Rol",
        "guard": "web",
        "categoria": "Seguridad"
    },
    {
        "name": "roles.bulk_delete",
        "description": "Eliminación Masiva de Roles",
        "guard": "web",
        "categoria": "Seguridad"
    },
    {
        "name": "permissions.list",
        "description": "Listar Permisos",
        "guard": "web",
        "categoria": "Seguridad"
    },
    {
        "name": "permissions.view",
        "description": "Ver Permiso",
        "guard": "web",
        "categoria": "Seguridad"
    },
    {
        "name": "permissions.create",
        "description": "Crear Permiso",
        "guard": "web",
        "categoria": "Seguridad"
    },
    {
        "name": "permissions.edit",
        "description": "Editar Permiso",
        "guard": "web",
        "categoria": "Seguridad"
    },
    {
        "name": "permissions.delete",
        "description": "Eliminar Permiso",
        "guard": "web",
        "categoria": "Seguridad"
    },
    {
        "name": "permissions.bulk_delete",
        "description": "Eliminación Masiva de Permisos",
        "guard": "web",
        "categoria": "Seguridad"
    },
    {
        "name": "categories.list",
        "description": "Listar Categorías de Permisos",
        "guard": "web",
        "categoria": "Seguridad"
    },
    {
        "name": "categories.view",
        "description": "Ver Categoría de Permiso",
        "guard": "web",
        "categoria": "Seguridad"
    },
    {
        "name": "categories.create",
        "description": "Crear Categoría de Permiso",
        "guard": "web",
        "categoria": "Seguridad"
    },
    {
        "name": "categories.edit",
        "description": "Editar Categoría de Permiso",
        "guard": "web",
        "categoria": "Seguridad"
    },
    {
        "name": "categories.update",
        "description": "Actualizar Categoría de Permiso",
        "guard": "web",
        "categoria": "Seguridad"
    },
    {
        "name": "categories.delete",
        "description": "Eliminar Categoría de Permiso",
        "guard": "web",
        "categoria": "Seguridad"
    },
    {
        "name": "categories.bulk_delete",
        "description": "Eliminación Masiva de Categorías de Permisos",
        "guard": "web",
        "categoria": "Seguridad"
    },
    {
        "name": "products.list",
        "description": "Listar Productos",
        "guard": "web",
        "categoria": "Almacén"
    },
    {
        "name": "products.view",
        "description": "Ver Producto",
        "guard": "web",
        "categoria": "Almacén"
    },
    {
        "name": "products.create",
        "description": "Crear Producto",
        "guard": "web",
        "categoria": "Almacén"
    },
    {
        "name": "products.edit",
        "description": "Editar Producto",
        "guard": "web",
        "categoria": "Almacén"
    },
    {
        "name": "products.delete",
        "description": "Eliminar Producto",
        "guard": "web",
        "categoria": "Almacén"
    },
    {
        "name": "products.bulk_delete",
        "description": "Eliminación Masiva de Productos",
        "guard": "web",
        "categoria": "Almacén"
    },
    {
        "name": "products.inventories.create",
        "description": "Crear Inventario de Producto",
        "guard": "web",
        "categoria": "Almacén"
    },
    {
        "name": "products.inventories.edit.view",
        "description": "Ver Modal para Editar Inventario de Producto",
        "guard": "web",
        "categoria": "Almacén"
    },
    {
        "name": "products.inventories.edit",
        "description": "Editar Inventario de Producto",
        "guard": "web",
        "categoria": "Almacén"
    },
    {
        "name": "products.inventories.view",
        "description": "Ver Inventario de Producto",
        "guard": "web",
        "categoria": "Almacén"
    },
    {
        "name": "products.inventories.delete",
        "description": "Eliminar Inventario de Producto",
        "guard": "web",
        "categoria": "Almacén"
    },
    {
        "name": "products.inventories.bulk_delete",
        "description": "Eliminación Masiva de Inventarios de Producto",
        "guard": "web",
        "categoria": "Almacén"
    },
    {
        "name": "services.list",
        "description": "Listar Servicios",
        "guard": "web",
        "categoria": "Almacén"
    },
    {
        "name": "services.view",
        "description": "Ver Servicio",
        "guard": "web",
        "categoria": "Almacén"
    },
    {
        "name": "services.create",
        "description": "Crear Servicio",
        "guard": "web",
        "categoria": "Almacén"
    },
    {
        "name": "services.edit",
        "description": "Editar Servicio",
        "guard": "web",
        "categoria": "Almacén"
    },
    {
        "name": "services.delete",
        "description": "Eliminar Servicio",
        "guard": "web",
        "categoria": "Almacén"
    },
    {
        "name": "services.bulk_delete",
        "description": "Eliminación Masiva de Servicios",
        "guard": "web",
        "categoria": "Almacén"
    },
    {
        "name": "services.products.create",
        "description": "Crear Producto en Servicio",
        "guard": "web",
        "categoria": "Almacén"
    },
    {
        "name": "services.products.attach",
        "description": "Asociar Producto existente en Servicio",
        "guard": "web",
        "categoria": "Almacén"
    },
    {
        "name": "services.products.edit.view",
        "description": "Ver Modal para Editar Producto en Servicio",
        "guard": "web",
        "categoria": "Almacén"
    },
    {
        "name": "services.products.edit",
        "description": "Editar Producto en Servicio",
        "guard": "web",
        "categoria": "Almacén"
    },
    {
        "name": "services.products.view",
        "description": "Ver Productos en Servicio",
        "guard": "web",
        "categoria": "Almacén"
    },
    {
        "name": "services.products.delete",
        "description": "Eliminar Producto en Servicio",
        "guard": "web",
        "categoria": "Almacén"
    },
    {
        "name": "services.products.bulk_delete",
        "description": "Eliminación Masiva de Productos en Servicio",
        "guard": "web",
        "categoria": "Almacén"
    },
    {
        "name": "inventories.list",
        "description": "Listar Inventarios",
        "guard": "web",
        "categoria": "Almacén"
    },
    {
        "name": "inventories.view",
        "description": "Ver Inventario",
        "guard": "web",
        "categoria": "Almacén"
    },
    {
        "name": "inventories.create",
        "description": "Crear Inventario",
        "guard": "web",
        "categoria": "Almacén"
    },
    {
        "name": "inventories.edit",
        "description": "Editar Inventario",
        "guard": "web",
        "categoria": "Almacén"
    },
    {
        "name": "inventories.delete",
        "description": "Eliminar Inventario",
        "guard": "web",
        "categoria": "Almacén"
    },
    {
        "name": "inventories.bulk_delete",
        "description": "Eliminación Masiva de Inventarios",
        "guard": "web",
        "categoria": "Almacén"
    },
    {
        "name": "inventory_modes.list",
        "description": "Listar Modos de Inventario",
        "guard": "web",
        "categoria": "Almacén"
    },
    {
        "name": "inventory_modes.view",
        "description": "Ver Modo de Inventario",
        "guard": "web",
        "categoria": "Almacén"
    },
    {
        "name": "inventory_modes.create",
        "description": "Crear Modo de Inventario",
        "guard": "web",
        "categoria": "Almacén"
    },
    {
        "name": "inventory_modes.edit",
        "description": "Editar Modo de Inventario",
        "guard": "web",
        "categoria": "Almacén"
    },
    {
        "name": "inventory_modes.move",
        "description": "Mover Stock entre Almacenes",
        "guard": "web",
        "categoria": "Almacén"
    },
    {
        "name": "inventory_modes.delete",
        "description": "Eliminar Modo de Inventario",
        "guard": "web",
        "categoria": "Almacén"
    },
    {
        "name": "inventory_modes.bulk_delete",
        "description": "Eliminación Masiva de Modos de Inventario",
        "guard": "web",
        "categoria": "Almacén"
    },
    {
        "name": "hozpitaliaciones.list",
        "description": "Listar Hozpitaliaciones",
        "guard": "web",
        "categoria": "Contabilidad"
    },
    {
        "name": "hozpitaliaciones.view",
        "description": "Ver Hozpitaliación",
        "guard": "web",
        "categoria": "Contabilidad"
    },
    {
        "name": "hozpitaliaciones.create",
        "description": "Crear Hozpitaliación",
        "guard": "web",
        "categoria": "Contabilidad"
    },
    {
        "name": "hozpitaliaciones.edit",
        "description": "Editar Hozpitaliación",
        "guard": "web",
        "categoria": "Contabilidad"
    },
    {
        "name": "hozpitaliaciones.delete",
        "description": "Eliminar Hozpitaliación",
        "guard": "web",
        "categoria": "Contabilidad"
    },
    {
        "name": "consultations.list",
        "description": "Listar Consultas",
        "guard": "web",
        "categoria": "Contabilidad"
    },
    {
        "name": "consultations.create",
        "description": "Crear Consulta",
        "guard": "web",
        "categoria": "Contabilidad"
    },
    {
        "name": "consultations.edit",
        "description": "Editar Consulta",
        "guard": "web",
        "categoria": "Contabilidad"
    },
    {
        "name": "consultations.delete",
        "description": "Eliminar Consulta",
        "guard": "web",
        "categoria": "Contabilidad"
    },
    {
        "name": "consultations.details.view",
        "description": "Ver Detalles en Consulta",
        "guard": "web",
        "categoria": "Contabilidad"
    },
    {
        "name": "consultations.details.attach",
        "description": "Asociar recurso existente en Consulta",
        "guard": "web",
        "categoria": "Contabilidad"
    },
    {
        "name": "consultations.details.edit.view",
        "description": "Ver Modal para Editar Detalle en Consulta",
        "guard": "web",
        "categoria": "Contabilidad"
    },
    {
        "name": "consultations.details.edit",
        "description": "Editar Detalle en Consulta",
        "guard": "web",
        "categoria": "Contabilidad"
    },
    {
        "name": "consultations.details.delete",
        "description": "Eliminar Detalle en Consulta",
        "guard": "web",
        "categoria": "Contabilidad"
    },
    {
        "name": "consultations.details.bulk_delete",
        "description": "Eliminación Masiva de Detalles en Consulta",
        "guard": "web",
        "categoria": "Contabilidad"
    },
    {
        "name": "consultations.payments.view",
        "description": "Ver Pagos en Consulta",
        "guard": "web",
        "categoria": "Contabilidad"
    },
    {
        "name": "consultations.payments.create",
        "description": "Crear Pago en Consulta",
        "guard": "web",
        "categoria": "Contabilidad"
    },
    {
        "name": "consultations.payments.edit.view",
        "description": "Ver Modal para Editar Pago en Consulta",
        "guard": "web",
        "categoria": "Contabilidad"
    },
    {
        "name": "consultations.payments.edit",
        "description": "Editar Pago en Consulta",
        "guard": "web",
        "categoria": "Contabilidad"
    },
    {
        "name": "consultations.inventories.view",
        "description": "Ver Inventario en Consulta",
        "guard": "web",
        "categoria": "Contabilidad"
    },
    {
        "name": "consultations.inventories.edit.view",
        "description": "Ver Modal para Editar Inventario en Consulta",
        "guard": "web",
        "categoria": "Contabilidad"
    },
    {
        "name": "consultations.inventories.edit",
        "description": "Editar Inventario en Consulta",
        "guard": "web",
        "categoria": "Contabilidad"
    },
    {
        "name": "quotations.details.view",
        "description": "Ver Detalles en Cotización",
        "guard": "web",
        "categoria": "Contabilidad"
    },
    {
        "name": "quotations.details.attach",
        "description": "Asociar recurso existente en Cotización",
        "guard": "web",
        "categoria": "Contabilidad"
    },
    {
        "name": "quotations.details.edit.view",
        "description": "Ver Modal para Editar Detalle en Cotización",
        "guard": "web",
        "categoria": "Contabilidad"
    },
    {
        "name": "quotations.details.edit",
        "description": "Editar Detalle en Cotización",
        "guard": "web",
        "categoria": "Contabilidad"
    },
    {
        "name": "quotations.details.delete",
        "description": "Eliminar Detalle en Cotización",
        "guard": "web",
        "categoria": "Contabilidad"
    },
    {
        "name": "quotations.details.bulk_delete",
        "description": "Eliminación Masiva de Detalles en Cotización",
        "guard": "web",
        "categoria": "Contabilidad"
    },
    {
        "name": "hospitalizations.inventories.edit",
        "description": "Editar Inventario en Hospitalización",
        "guard": "web",
        "categoria": "Contabilidad"
    },
    {
        "name": "hospitalizations.inventories.edit.view",
        "description": "Ver Modal para Editar Inventario en Hospitalización",
        "guard": "web",
        "categoria": "Contabilidad"
    },
    {
        "name": "inventories.import.view",
        "description": "Ver Modal para Importar Inventario",
        "guard": "web",
        "categoria": "Almacén"
    },
    {
        "name": "inventories.import",
        "description": "Importar Inventario",
        "guard": "web",
        "categoria": "Almacén"
    },
    {
        "name": "inventories.move_several.view",
        "description": "Ver Modal para Mover Varios Inventarios",
        "guard": "web",
        "categoria": "Almacén"
    },
    {
        "name": "inventories.move_several",
        "description": "Mover Varios Inventarios",
        "guard": "web",
        "categoria": "Almacén"
    },
    {
        "name": "inventories.move.view",
        "description": "Ver Opción para Mover Inventario",
        "guard": "web",
        "categoria": "Almacén"
    },
    {
        "name": "hospitalizations.inventories.view",
        "description": "Ver Inventario en Hospitalización",
        "guard": "web",
        "categoria": "Contabilidad"
    },
    {
        "name": "hospitalizations.payments.create",
        "description": "Crear Pago en Hospitalización",
        "guard": "web",
        "categoria": "Contabilidad"
    },
    {
        "name": "hospitalizations.payments.edit",
        "description": "Editar Pago en Hospitalización",
        "guard": "web",
        "categoria": "Contabilidad"
    },
    {
        "name": "hospitalizations.payments.edit.view",
        "description": "Ver Modal para Editar Pago en Hospitalización",
        "guard": "web",
        "categoria": "Contabilidad"
    },
    {
        "name": "hospitalizations.payments.view",
        "description": "Ver Pago en Hospitalización",
        "guard": "web",
        "categoria": "Contabilidad"
    },
    {
        "name": "hospitalizations.details.create",
        "description": "Crear recurso en Hospitalización",
        "guard": "web",
        "categoria": "Contabilidad"
    },
    {
        "name": "hospitalizations.details.attach",
        "description": "Asociar recurso existente en Hospitalización",
        "guard": "web",
        "categoria": "Contabilidad"
    },
    {
        "name": "hospitalizations.details.reference_values.create",
        "description": "Crear Valor Referencial en Hospitalización",
        "guard": "web",
        "categoria": "Contabilidad"
    },
    {
        "name": "hospitalizations.details.edit.view",
        "description": "Ver Modal para Editar Detalle en Hospitalización",
        "guard": "web",
        "categoria": "Contabilidad"
    },
    {
        "name": "hospitalizations.details.edit",
        "description": "Editar Detalle en Hospitalización",
        "guard": "web",
        "categoria": "Contabilidad"
    },
    {
        "name": "hospitalizations.details.reference_value_results.add",
        "description": "Cargar Resultados de Valores Referenciales en Hospitalización",
        "guard": "web",
        "categoria": "Contabilidad"
    },
    {
        "name": "hospitalizations.details.delete",
        "description": "Eliminar Detalle en Hospitalización",
        "guard": "web",
        "categoria": "Contabilidad"
    },
    {
        "name": "hospitalizations.details.view",
        "description": "Ver Detalles en Hospitalización",
        "guard": "web",
        "categoria": "Contabilidad"
    },
    {
        "name": "laboratories.details.attach",
        "description": "Asociar examen existente en Laboratorio",
        "guard": "web",
        "categoria": "Contabilidad"
    },
    {
        "name": "laboratories.details.create",
        "description": "Crear examen en Laboratorio",
        "guard": "web",
        "categoria": "Contabilidad"
    },
    {
        "name": "laboratories.details.reference_values.create",
        "description": "Crear Valor Referencial en Laboratorio",
        "guard": "web",
        "categoria": "Contabilidad"
    },
    {
        "name": "laboratories.details.reference_value_results.add",
        "description": "Cargar Resultados de Valores Referenciales en Laboratorio",
        "guard": "web",
        "categoria": "Contabilidad"
    },
    {
        "name": "laboratories.details.delete",
        "description": "Eliminar examen en Laboratorio",
        "guard": "web",
        "categoria": "Contabilidad"
    },
    {
        "name": "laboratories.details.bulk_delete",
        "description": "Eliminación Masiva de exámenes en Laboratorio",
        "guard": "web",
        "categoria": "Contabilidad"
    },
    {
        "name": "laboratories.details.view",
        "description": "Ver exámenes en Laboratorio",
        "guard": "web",
        "categoria": "Contabilidad"
    },
    {
        "name": "laboratories.payments.create",
        "description": "Crear Pago en Laboratorio",
        "guard": "web",
        "categoria": "Contabilidad"
    },
    {
        "name": "laboratories.payments.edit.view",
        "description": "Ver Modal para Editar Pago en Laboratorio",
        "guard": "web",
        "categoria": "Contabilidad"
    },
    {
        "name": "laboratories.payments.edit",
        "description": "Editar Pago en Laboratorio",
        "guard": "web",
        "categoria": "Contabilidad"
    },
    {
        "name": "laboratories.payments.view",
        "description": "Ver Pago en Laboratorio",
        "guard": "web",
        "categoria": "Contabilidad"
    },
    {
        "name": "laboratories.details.delete",
        "description": "Eliminar Detalle en Laboratorio",
        "guard": "web",
        "categoria": "Contabilidad"
    },
    {
        "name": "laboratories.details.bulk_delete",
        "description": "Eliminación Masiva de Detalles en Laboratorio",
        "guard": "web",
        "categoria": "Contabilidad"
    },
    {
        "name": "laboratories.details.reference_values.create",
        "description": "Crear Valor Referencial en Laboratorio",
        "guard": "web",
        "categoria": "Contabilidad"
    },
    {
        "name": "laboratories.details.reference_value_results.add",
        "description": "Cargar Resultados de Valores Referenciales en Laboratorio",
        "guard": "web",
        "categoria": "Contabilidad"
    },
    {
        "name": "warehouses.list",
        "description": "Listar Almacenes",
        "guard": "web",
        "categoria": "Almacén"
    },
    {
        "name": "warehouses.view",
        "description": "Ver Almacén",
        "guard": "web",
        "categoria": "Almacén"
    },
    {
        "name": "warehouses.create",
        "description": "Crear Almacén",
        "guard": "web",
        "categoria": "Almacén"
    },
    {
        "name": "warehouses.edit",
        "description": "Editar Almacén",
        "guard": "web",
        "categoria": "Almacén"
    },
    {
        "name": "warehouses.delete",
        "description": "Eliminar Almacén",
        "guard": "web",
        "categoria": "Almacén"
    },
    {
        "name": "warehouses.bulk_delete",
        "description": "Eliminación Masiva de Almacenes",
        "guard": "web",
        "categoria": "Almacén"
    },
    {
        "name": "doctors.list",
        "description": "Listar Doctores",
        "guard": "web",
        "categoria": "RRHH"
    },
    {
        "name": "doctors.view",
        "description": "Ver Doctor",
        "guard": "web",
        "categoria": "RRHH"
    },
    {
        "name": "doctors.create",
        "description": "Crear Doctor",
        "guard": "web",
        "categoria": "RRHH"
    },
    {
        "name": "doctors.edit",
        "description": "Editar Doctor",
        "guard": "web",
        "categoria": "RRHH"
    },
    {
        "name": "doctors.delete",
        "description": "Eliminar Doctor",
        "guard": "web",
        "categoria": "RRHH"
    },
    {
        "name": "doctors.bulk_delete",
        "description": "Eliminación Masiva de Doctores",
        "guard": "web",
        "categoria": "RRHH"
    },
    {
        "name": "patients.list",
        "description": "Listar Pacientes",
        "guard": "web",
        "categoria": "RRHH"
    },
    {
        "name": "patients.view",
        "description": "Ver Paciente",
        "guard": "web",
        "categoria": "RRHH"
    },
    {
        "name": "patients.create",
        "description": "Crear Paciente",
        "guard": "web",
        "categoria": "RRHH"
    },
    {
        "name": "patients.edit",
        "description": "Editar Paciente",
        "guard": "web",
        "categoria": "RRHH"
    },
    {
        "name": "patients.delete",
        "description": "Eliminar Paciente",
        "guard": "web",
        "categoria": "RRHH"
    },
    {
        "name": "patients.bulk_delete",
        "description": "Eliminación Masiva de Pacientes",
        "guard": "web",
        "categoria": "RRHH"
    },
    {
        "name": "specializations.list",
        "description": "Listar Especializaciones",
        "guard": "web",
        "categoria": "RRHH"
    },
    {
        "name": "specializations.view",
        "description": "Ver Especialización",
        "guard": "web",
        "categoria": "RRHH"
    },
    {
        "name": "specializations.create",
        "description": "Crear Especialización",
        "guard": "web",
        "categoria": "RRHH"
    },
    {
        "name": "specializations.edit",
        "description": "Editar Especialización",
        "guard": "web",
        "categoria": "RRHH"
    },
    {
        "name": "specializations.delete",
        "description": "Eliminar Especialización",
        "guard": "web",
        "categoria": "RRHH"
    },
    {
        "name": "specializations.bulk_delete",
        "description": "Eliminación Masiva de Especializaciones",
        "guard": "web",
        "categoria": "RRHH"
    },
    {
        "name": "departments.list",
        "description": "Listar Departamentos",
        "guard": "web",
        "categoria": "RRHH"
    },
    {
        "name": "departments.view",
        "description": "Ver Departamento",
        "guard": "web",
        "categoria": "RRHH"
    },
    {
        "name": "departments.create",
        "description": "Crear Departamento",
        "guard": "web",
        "categoria": "RRHH"
    },
    {
        "name": "departments.edit",
        "description": "Editar Departamento",
        "guard": "web",
        "categoria": "RRHH"
    },
    {
        "name": "departments.delete",
        "description": "Eliminar Departamento",
        "guard": "web",
        "categoria": "RRHH"
    },
    {
        "name": "departments.bulk_delete",
        "description": "Eliminación Masiva de Departamentos",
        "guard": "web",
        "categoria": "RRHH"
    },
    {
        "name": "currencies.list",
        "description": "Listar Monedas",
        "guard": "web",
        "categoria": "Configuración"
    },
    {
        "name": "currencies.view",
        "description": "Ver Moneda",
        "guard": "web",
        "categoria": "Configuración"
    },
    {
        "name": "currencies.create",
        "description": "Crear Moneda",
        "guard": "web",
        "categoria": "Configuración"
    },
    {
        "name": "currencies.edit",
        "description": "Editar Moneda",
        "guard": "web",
        "categoria": "Configuración"
    },
    {
        "name": "currencies.delete",
        "description": "Eliminar Moneda",
        "guard": "web",
        "categoria": "Configuración"
    },
    {
        "name": "currencies.bulk_delete",
        "description": "Eliminación Masiva de Monedas",
        "guard": "web",
        "categoria": "Configuración"
    },
    {
        "name": "exams.list",
        "description": "Listar Exámenes",
        "guard": "web",
        "categoria": "Laboratorio"
    },
    {
        "name": "exams.view",
        "description": "Ver Examen",
        "guard": "web",
        "categoria": "Laboratorio"
    },
    {
        "name": "exams.create",
        "description": "Crear Examen",
        "guard": "web",
        "categoria": "Laboratorio"
    },
    {
        "name": "exams.edit",
        "description": "Editar Examen",
        "guard": "web",
        "categoria": "Laboratorio"
    },
    {
        "name": "exams.delete",
        "description": "Eliminar Examen",
        "guard": "web",
        "categoria": "Laboratorio"
    },
    {
        "name": "exams.bulk_delete",
        "description": "Eliminación Masiva de Exámenes",
        "guard": "web",
        "categoria": "Laboratorio"
    },
    {
        "name": "exams.reference_values.create",
        "description": "Crear Valor Referencial en Examen",
        "guard": "web",
        "categoria": "Laboratorio"
    },
    {
        "name": "exams.reference_values.edit.view",
        "description": "Ver Modal para Editar Valor Referencial en Examen",
        "guard": "web",
        "categoria": "Laboratorio"
    },
    {
        "name": "exams.reference_values.edit",
        "description": "Editar Valor Referencial en Examen",
        "guard": "web",
        "categoria": "Laboratorio"
    },
    {
        "name": "exams.reference_values.view",
        "description": "Ver Valores Referenciales en Examen",
        "guard": "web",
        "categoria": "Laboratorio"
    },
    {
        "name": "exams.reference_values.delete",
        "description": "Eliminar Valor Referencial en Examen",
        "guard": "web",
        "categoria": "Laboratorio"
    },
    {
        "name": "exams.reference_values.bulk_delete",
        "description": "Eliminación Masiva de Valores Referenciales en Examen",
        "guard": "web",
        "categoria": "Laboratorio"
    },
    {
        "name": "exam_categories.list",
        "description": "Listar Categorías de Examen",
        "guard": "web",
        "categoria": "Laboratorio"
    },
    {
        "name": "exam_categories.view",
        "description": "Ver Categoría de Examen",
        "guard": "web",
        "categoria": "Laboratorio"
    },
    {
        "name": "exam_categories.create",
        "description": "Crear Categoría de Examen",
        "guard": "web",
        "categoria": "Laboratorio"
    },
    {
        "name": "exam_categories.edit",
        "description": "Editar Categoría de Examen",
        "guard": "web",
        "categoria": "Laboratorio"
    },
    {
        "name": "exam_categories.delete",
        "description": "Eliminar Categoría de Examen",
        "guard": "web",
        "categoria": "Laboratorio"
    },
    {
        "name": "exam_categories.bulk_delete",
        "description": "Eliminación Masiva de Categorías de Examen",
        "guard": "web",
        "categoria": "Laboratorio"
    },
    {
        "name": "payment_methods.list",
        "description": "Listar Métodos de Pago",
        "guard": "web",
        "categoria": "Configuración"
    },
    {
        "name": "payment_methods.view",
        "description": "Ver Método de Pago",
        "guard": "web",
        "categoria": "Configuración"
    },
    {
        "name": "payment_methods.create",
        "description": "Crear Método de Pago",
        "guard": "web",
        "categoria": "Configuración"
    },
    {
        "name": "payment_methods.edit",
        "description": "Editar Método de Pago",
        "guard": "web",
        "categoria": "Configuración"
    },
    {
        "name": "payment_methods.delete",
        "description": "Eliminar Método de Pago",
        "guard": "web",
        "categoria": "Configuración"
    },
    {
        "name": "payment_methods.bulk_delete",
        "description": "Eliminación Masiva de Métodos de Pago",
        "guard": "web",
        "categoria": "Configuración"
    },
    {
        "name": "product_categories.list",
        "description": "Listar Categorías de Productos",
        "guard": "web",
        "categoria": "Configuración"
    },
    {
        "name": "product_categories.view",
        "description": "Ver Categoría de Producto",
        "guard": "web",
        "categoria": "Configuración"
    },
    {
        "name": "product_categories.create",
        "description": "Crear Categoría de Producto",
        "guard": "web",
        "categoria": "Configuración"
    },
    {
        "name": "product_categories.edit",
        "description": "Editar Categoría de Producto",
        "guard": "web",
        "categoria": "Configuración"
    },
    {
        "name": "product_categories.delete",
        "description": "Eliminar Categoría de Producto",
        "guard": "web",
        "categoria": "Configuración"
    },
    {
        "name": "product_categories.bulk_delete",
        "description": "Eliminación Masiva de Categorías de Producto",
        "guard": "web",
        "categoria": "Configuración"
    },
    {
        "name": "product_service_details.list",
        "description": "Listar Detalles de Producto/Servicio",
        "guard": "web",
        "categoria": "Configuración"
    },
    {
        "name": "product_service_details.view",
        "description": "Ver Detalle de Producto/Servicio",
        "guard": "web",
        "categoria": "Configuración"
    },
    {
        "name": "product_service_details.create",
        "description": "Crear Detalle de Producto/Servicio",
        "guard": "web",
        "categoria": "Configuración"
    },
    {
        "name": "product_service_details.edit",
        "description": "Editar Detalle de Producto/Servicio",
        "guard": "web",
        "categoria": "Configuración"
    },
    {
        "name": "product_service_details.delete",
        "description": "Eliminar Detalle de Producto/Servicio",
        "guard": "web",
        "categoria": "Configuración"
    },
    {
        "name": "reference_values.list",
        "description": "Listar Valores de Referencia",
        "guard": "web",
        "categoria": "Configuración"
    },
    {
        "name": "reference_values.view",
        "description": "Ver Valor de Referencia",
        "guard": "web",
        "categoria": "Configuración"
    },
    {
        "name": "reference_values.create",
        "description": "Crear Valor de Referencia",
        "guard": "web",
        "categoria": "Configuración"
    },
    {
        "name": "reference_values.edit",
        "description": "Editar Valor de Referencia",
        "guard": "web",
        "categoria": "Configuración"
    },
    {
        "name": "reference_values.delete",
        "description": "Eliminar Valor de Referencia",
        "guard": "web",
        "categoria": "Configuración"
    },
    {
        "name": "reference_values.bulk_delete",
        "description": "Eliminación Masiva de Valores de Referencia",
        "guard": "web",
        "categoria": "Configuración"
    },
    {
        "name": "reference_value_results.edit.view",
        "description": "Ver Modal para Editar Resultados de Valores Referenciales",
        "guard": "web",
        "categoria": "Contabilidad"
    },
    {
        "name": "reference_value_results.edit",
        "description": "Editar Resultados de Valores Referenciales",
        "guard": "web",
        "categoria": "Contabilidad"
    },
    {
        "name": "rooms.list",
        "description": "Listar Habitaciones",
        "guard": "web",
        "categoria": "Configuración"
    },
    {
        "name": "rooms.view",
        "description": "Ver Habitación",
        "guard": "web",
        "categoria": "Configuración"
    },
    {
        "name": "rooms.create",
        "description": "Crear Habitación",
        "guard": "web",
        "categoria": "Configuración"
    },
    {
        "name": "rooms.edit",
        "description": "Editar Habitación",
        "guard": "web",
        "categoria": "Configuración"
    },
    {
        "name": "rooms.delete",
        "description": "Eliminar Habitación",
        "guard": "web",
        "categoria": "Configuración"
    },
    {
        "name": "rooms.bulk_delete",
        "description": "Eliminación Masiva de Habitaciones",
        "guard": "web",
        "categoria": "Configuración"
    },
    {
        "name": "service_categories.list",
        "description": "Listar Categorías de Servicios",
        "guard": "web",
        "categoria": "Configuración"
    },
    {
        "name": "service_categories.view",
        "description": "Ver Categoría de Servicio",
        "guard": "web",
        "categoria": "Configuración"
    },
    {
        "name": "service_categories.create",
        "description": "Crear Categoría de Servicio",
        "guard": "web",
        "categoria": "Configuración"
    },
    {
        "name": "service_categories.edit",
        "description": "Editar Categoría de Servicio",
        "guard": "web",
        "categoria": "Configuración"
    },
    {
        "name": "service_categories.delete",
        "description": "Eliminar Categoría de Servicio",
        "guard": "web",
        "categoria": "Configuración"
    },
    {
        "name": "service_categories.bulk_delete",
        "description": "Eliminación Masiva de Categorías de Servicio",
        "guard": "web",
        "categoria": "Configuración"
    },
    {
        "name": "suppliers.list",
        "description": "Listar Proveedores",
        "guard": "web",
        "categoria": "Configuración"
    },
    {
        "name": "suppliers.view",
        "description": "Ver Proveedor",
        "guard": "web",
        "categoria": "Configuración"
    },
    {
        "name": "suppliers.create",
        "description": "Crear Proveedor",
        "guard": "web",
        "categoria": "Configuración"
    },
    {
        "name": "suppliers.edit",
        "description": "Editar Proveedor",
        "guard": "web",
        "categoria": "Configuración"
    },
    {
        "name": "suppliers.delete",
        "description": "Eliminar Proveedor",
        "guard": "web",
        "categoria": "Configuración"
    },
    {
        "name": "suppliers.bulk_delete",
        "description": "Eliminación Masiva de Proveedores",
        "guard": "web",
        "categoria": "Configuración"
    },
    {
        "name": "type_documents.list",
        "description": "Listar Tipos de Documentos",
        "guard": "web",
        "categoria": "Configuración"
    },
    {
        "name": "type_documents.view",
        "description": "Ver Tipo de Documento",
        "guard": "web",
        "categoria": "Configuración"
    },
    {
        "name": "type_documents.create",
        "description": "Crear Tipo de Documento",
        "guard": "web",
        "categoria": "Configuración"
    },
    {
        "name": "type_documents.edit",
        "description": "Editar Tipo de Documento",
        "guard": "web",
        "categoria": "Configuración"
    },
    {
        "name": "type_documents.delete",
        "description": "Eliminar Tipo de Documento",
        "guard": "web",
        "categoria": "Configuración"
    },
    {
        "name": "type_documents.bulk_delete",
        "description": "Eliminación Masiva de Tipos de Documento",
        "guard": "web",
        "categoria": "Configuración"
    },
    {
        "name": "units.list",
        "description": "Listar Unidades de Medida",
        "guard": "web",
        "categoria": "Configuración"
    },
    {
        "name": "units.view",
        "description": "Ver Unidad de Medida",
        "guard": "web",
        "categoria": "Configuración"
    },
    {
        "name": "units.create",
        "description": "Crear Unidad de Medida",
        "guard": "web",
        "categoria": "Configuración"
    },
    {
        "name": "units.edit",
        "description": "Editar Unidad de Medida",
        "guard": "web",
        "categoria": "Configuración"
    },
    {
        "name": "units.delete",
        "description": "Eliminar Unidad de Medida",
        "guard": "web",
        "categoria": "Configuración"
    },
    {
        "name": "units.bulk_delete",
        "description": "Eliminación Masiva de Unidades de Medida",
        "guard": "web",
        "categoria": "Configuración"
    },
    {
        "name": "unit_categories.list",
        "description": "Listar Categorías de Unidades",
        "guard": "web",
        "categoria": "Configuración"
    },
    {
        "name": "unit_categories.view",
        "description": "Ver Categoría de Unidad",
        "guard": "web",
        "categoria": "Configuración"
    },
    {
        "name": "unit_categories.create",
        "description": "Crear Categoría de Unidad",
        "guard": "web",
        "categoria": "Configuración"
    },
    {
        "name": "unit_categories.edit",
        "description": "Editar Categoría de Unidad",
        "guard": "web",
        "categoria": "Configuración"
    },
    {
        "name": "unit_categories.delete",
        "description": "Eliminar Categoría de Unidad",
        "guard": "web",
        "categoria": "Configuración"
    },
    {
        "name": "unit_categories.bulk_delete",
        "description": "Eliminación Masiva de Categorías de Unidad",
        "guard": "web",
        "categoria": "Configuración"
    },
    {
        "name": "entries.list",
        "description": "Listar Entradas",
        "guard": "web",
        "categoria": "Contabilidad"
    },
    {
        "name": "entries.view",
        "description": "Ver Entrada",
        "guard": "web",
        "categoria": "Contabilidad"
    },
    {
        "name": "entries.create",
        "description": "Crear Entrada",
        "guard": "web",
        "categoria": "Contabilidad"
    },
    {
        "name": "entries.edit",
        "description": "Editar Entrada",
        "guard": "web",
        "categoria": "Contabilidad"
    },
    {
        "name": "entries.delete",
        "description": "Eliminar Entrada",
        "guard": "web",
        "categoria": "Contabilidad"
    },
    {
        "name": "entries.details.taxes.view",
        "description": "Ver Impuestos en Detalle de Entrada",
        "guard": "web",
        "categoria": "Contabilidad"
    },
    {
        "name": "entries.details.batches.view",
        "description": "Ver Lotes en Detalle de Entrada",
        "guard": "web",
        "categoria": "Contabilidad"
    },
    {
        "name": "entries.discounts.view",
        "description": "Ver Descuentos en Entrada",
        "guard": "web",
        "categoria": "Contabilidad"
    },
    {
        "name": "entries.discounts.create",
        "description": "Crear Descuento en Entrada",
        "guard": "web",
        "categoria": "Contabilidad"
    },
    {
        "name": "entries.discounts.edit",
        "description": "Editar Descuento en Entrada",
        "guard": "web",
        "categoria": "Contabilidad"
    },
    {
        "name": "entries.discounts.edit.view",
        "description": "Ver Modal para Editar Descuento en Entrada",
        "guard": "web",
        "categoria": "Contabilidad"
    },
    {
        "name": "entries.discounts.delete",
        "description": "Eliminar Descuento en Entrada",
        "guard": "web",
        "categoria": "Contabilidad"
    },
    {
        "name": "entries.discounts.bulk_delete",
        "description": "Eliminación Masiva de Descuentos en Entrada",
        "guard": "web",
        "categoria": "Contabilidad"
    },
    {
        "name": "entries.payments.create",
        "description": "Crear Pago en Entrada",
        "guard": "web",
        "categoria": "Contabilidad"
    },
    {
        "name": "entries.payments.edit",
        "description": "Editar Pago en Entrada",
        "guard": "web",
        "categoria": "Contabilidad"
    },
    {
        "name": "entries.payments.edit.view",
        "description": "Ver Modal para Editar Pago en Entrada",
        "guard": "web",
        "categoria": "Contabilidad"
    },
    {
        "name": "entries.payments.view",
        "description": "Ver Pago en Entrada",
        "guard": "web",
        "categoria": "Contabilidad"
    },
    {
        "name": "entries.inventories.edit",
        "description": "Editar Inventario en Entrada",
        "guard": "web",
        "categoria": "Contabilidad"
    },
    {
        "name": "entries.inventories.edit.view",
        "description": "Ver Modal para Editar Inventario en Entrada",
        "guard": "web",
        "categoria": "Contabilidad"
    },
    {
        "name": "entries.inventories.view",
        "description": "Ver Inventario en Entrada",
        "guard": "web",
        "categoria": "Contabilidad"
    },
    {
        "name": "entries.refunds.create",
        "description": "Crear Reembolso en Entrada",
        "guard": "web",
        "categoria": "Contabilidad"
    },
    {
        "name": "entries.refunds.edit",
        "description": "Editar Reembolso en Entrada",
        "guard": "web",
        "categoria": "Contabilidad"
    },
    {
        "name": "entries.refunds.edit.view",
        "description": "Ver Modal para Editar Reembolso en Entrada",
        "guard": "web",
        "categoria": "Contabilidad"
    },
    {
        "name": "entries.refunds.view",
        "description": "Ver Reembolso en Entrada",
        "guard": "web",
        "categoria": "Contabilidad"
    },
    {
        "name": "entries.refunds.delete",
        "description": "Eliminar Reembolso en Entrada",
        "guard": "web",
        "categoria": "Contabilidad"
    },
    {
        "name": "entries.refunds.bulk_delete",
        "description": "Eliminación Masiva de Reembolsos en Entrada",
        "guard": "web",
        "categoria": "Contabilidad"
    },
    {
        "name": "entries.details.create",
        "description": "Crear Detalle en Entrada",
        "guard": "web",
        "categoria": "Contabilidad"
    },
    {
        "name": "entries.details.attach",
        "description": "Asociar Detalle existente en Entrada",
        "guard": "web",
        "categoria": "Contabilidad"
    },
    {
        "name": "entries.details.edit",
        "description": "Editar Detalle en Entrada",
        "guard": "web",
        "categoria": "Contabilidad"
    },
    {
        "name": "entries.details.edit.view",
        "description": "Ver Modal para Editar Detalle en Entrada",
        "guard": "web",
        "categoria": "Contabilidad"
    },
    {
        "name": "entries.details.view",
        "description": "Ver Detalle en Entrada",
        "guard": "web",
        "categoria": "Contabilidad"
    },
    {
        "name": "entries.details.delete",
        "description": "Eliminar Detalle en Entrada",
        "guard": "web",
        "categoria": "Contabilidad"
    },
    {
        "name": "entries.details.return",
        "description": "Devolver Producto en Entrada",
        "guard": "web",
        "categoria": "Contabilidad"
    },
    {
        "name": "expenses.list",
        "description": "Listar Gastos",
        "guard": "web",
        "categoria": "Contabilidad"
    },
    {
        "name": "expenses.view",
        "description": "Ver Gasto",
        "guard": "web",
        "categoria": "Contabilidad"
    },
    {
        "name": "expenses.create",
        "description": "Crear Gasto",
        "guard": "web",
        "categoria": "Contabilidad"
    },
    {
        "name": "expenses.edit",
        "description": "Editar Gasto",
        "guard": "web",
        "categoria": "Contabilidad"
    },
    {
        "name": "expenses.delete",
        "description": "Eliminar Gasto",
        "guard": "web",
        "categoria": "Contabilidad"
    },
    {
        "name": "expenses.bulk_delete",
        "description": "Eliminación Masiva de Gastos",
        "guard": "web",
        "categoria": "Contabilidad"
    },
    {
        "name": "expense_categories.list",
        "description": "Listar Categorías de Gastos",
        "guard": "web",
        "categoria": "Configuración"
    },
    {
        "name": "expense_categories.view",
        "description": "Ver Categoría de Gasto",
        "guard": "web",
        "categoria": "Configuración"
    },
    {
        "name": "expense_categories.create",
        "description": "Crear Categoría de Gasto",
        "guard": "web",
        "categoria": "Configuración"
    },
    {
        "name": "expense_categories.edit",
        "description": "Editar Categoría de Gasto",
        "guard": "web",
        "categoria": "Configuración"
    },
    {
        "name": "expense_categories.delete",
        "description": "Eliminar Categoría de Gasto",
        "guard": "web",
        "categoria": "Configuración"
    },
    {
        "name": "expense_categories.bulk_delete",
        "description": "Eliminación Masiva de Categorías de Gastos",
        "guard": "web",
        "categoria": "Configuración"
    },
    {
        "name": "invoices.list",
        "description": "Listar Facturas",
        "guard": "web",
        "categoria": "Contabilidad"
    },
    {
        "name": "invoices.view",
        "description": "Ver Factura",
        "guard": "web",
        "categoria": "Contabilidad"
    },
    {
        "name": "invoices.create",
        "description": "Crear Factura",
        "guard": "web",
        "categoria": "Contabilidad"
    },
    {
        "name": "invoices.edit",
        "description": "Editar Factura",
        "guard": "web",
        "categoria": "Contabilidad"
    },
    {
        "name": "invoices.delete",
        "description": "Eliminar Factura",
        "guard": "web",
        "categoria": "Contabilidad"
    },
    {
        "name": "invoices.inventories.edit",
        "description": "Editar Inventario en Factura",
        "guard": "web",
        "categoria": "Contabilidad"
    },
    {
        "name": "invoices.inventories.edit.view",
        "description": "Ver Modal para Editar Inventario en Factura",
        "guard": "web",
        "categoria": "Contabilidad"
    },
    {
        "name": "invoices.inventories.view",
        "description": "Ver Inventario en Factura",
        "guard": "web",
        "categoria": "Contabilidad"
    },
    {
        "name": "invoices.details.view",
        "description": "Ver detalle de Factura",
        "guard": "web",
        "categoria": "Contabilidad"
    },
    {
        "name": "invoices.details.edit.view",
        "description": "Editar detalle de Factura Modal",
        "guard": "web",
        "categoria": "Contabilidad"
    },
    {
        "name": "invoices.details.edit",
        "description": "Editar detalle de Factura",
        "guard": "web",
        "categoria": "Contabilidad"
    },
    {
        "name": "invoices.details.delete",
        "description": "Eliminar detalle de Factura",
        "guard": "web",
        "categoria": "Contabilidad"
    },
    {
        "name": "invoices.details.attach",
        "description": "Crear detalle de Factura con recurso existente",
        "guard": "web",
        "categoria": "Contabilidad"
    },
    {
        "name": "invoices.details.bulk_delete",
        "description": "Eliminación Masiva de Detalles en Factura",
        "guard": "web",
        "categoria": "Contabilidad"
    },
    {
        "name": "invoices.payments.create",
        "description": "Crear Pago en Factura",
        "guard": "web",
        "categoria": "Contabilidad"
    },
    {
        "name": "invoices.payments.edit",
        "description": "Editar Pago en Factura",
        "guard": "web",
        "categoria": "Contabilidad"
    },
    {
        "name": "invoices.payments.edit.view",
        "description": "Ver Modal para Editar Pago en Factura",
        "guard": "web",
        "categoria": "Contabilidad"
    },
    {
        "name": "invoice_details_batches.create",
        "description": "Crear Lote en Detalle de Factura",
        "guard": "web",
        "categoria": "Contabilidad"
    },
    {
        "name": "invoice_details_batches.edit.view",
        "description": "Ver Modal para Editar Lote en Detalle de Factura",
        "guard": "web",
        "categoria": "Contabilidad"
    },
    {
        "name": "invoice_details_batches.edit",
        "description": "Editar Lote en Detalle de Factura",
        "guard": "web",
        "categoria": "Contabilidad"
    },
    {
        "name": "invoice_details_batches.delete",
        "description": "Eliminar Lote en Detalle de Factura",
        "guard": "web",
        "categoria": "Contabilidad"
    },
    {
        "name": "invoice_details_taxes.create",
        "description": "Crear Impuesto en Detalle de Factura",
        "guard": "web",
        "categoria": "Contabilidad"
    },
    {
        "name": "invoice_details_taxes.edit.view",
        "description": "Ver Modal para Editar Impuesto en Detalle de Factura",
        "guard": "web",
        "categoria": "Contabilidad"
    },
    {
        "name": "invoice_details_taxes.edit",
        "description": "Editar Impuesto en Detalle de Factura",
        "guard": "web",
        "categoria": "Contabilidad"
    },
    {
        "name": "invoice_details_taxes.delete",
        "description": "Eliminar Impuesto en Detalle de Factura",
        "guard": "web",
        "categoria": "Contabilidad"
    },
    {
        "name": "invoices.payments.view",
        "description": "Ver Pago en Factura",
        "guard": "web",
        "categoria": "Contabilidad"
    },
    {
        "name": "laboratorio.list",
        "description": "Listar Laboratorio",
        "guard": "web",
        "categoria": "Contabilidad"
    },
    {
        "name": "laboratorio.view",
        "description": "Ver Laboratorio",
        "guard": "web",
        "categoria": "Contabilidad"
    },
    {
        "name": "laboratorio.create",
        "description": "Crear Laboratorio",
        "guard": "web",
        "categoria": "Contabilidad"
    },
    {
        "name": "laboratorio.edit",
        "description": "Editar Laboratorio",
        "guard": "web",
        "categoria": "Contabilidad"
    },
    {
        "name": "laboratorio.delete",
        "description": "Eliminar Laboratorio",
        "guard": "web",
        "categoria": "Contabilidad"
    },
    {
        "name": "quotations.list",
        "description": "Listar Cotizaciones",
        "guard": "web",
        "categoria": "Contabilidad"
    },
    {
        "name": "quotations.view",
        "description": "Ver Cotización",
        "guard": "web",
        "categoria": "Contabilidad"
    },
    {
        "name": "quotations.create",
        "description": "Crear Cotización",
        "guard": "web",
        "categoria": "Contabilidad"
    },
    {
        "name": "quotations.edit",
        "description": "Editar Cotización",
        "guard": "web",
        "categoria": "Contabilidad"
    },
    {
        "name": "quotations.delete",
        "description": "Eliminar Cotización",
        "guard": "web",
        "categoria": "Contabilidad"
    },
    {
        "name": "users.list",
        "description": "Listar Usuarios",
        "guard": "web",
        "categoria": "Administración"
    },
    {
        "name": "users.view",
        "description": "Ver Usuario",
        "guard": "web",
        "categoria": "Administración"
    },
    {
        "name": "users.create",
        "description": "Crear Usuario",
        "guard": "web",
        "categoria": "Administración"
    },
    {
        "name": "users.edit",
        "description": "Editar Usuario",
        "guard": "web",
        "categoria": "Administración"
    },
    {
        "name": "users.delete",
        "description": "Eliminar Usuario",
        "guard": "web",
        "categoria": "Administración"
    },
    {
        "name": "users.bulk_delete",
        "description": "Eliminación Masiva de Usuarios",
        "guard": "web",
        "categoria": "Administración"
    },
    {
        "name": "reports.list",
        "description": "Ver Reportes de Facturas",
        "guard": "web",
        "categoria": "Reportes"
    }
]
